{
    "issue-type-scheme":
    {
        "name": "project.issuetype.scheme.name",
        "description": "project.issuetype.scheme.description",
        "issue-types": [
            {
                "key": "issueType1",
                "name": "New Feature",
                "description": "A new feature of the product, which has yet to be developed.",
                "icon": "/images/icons/newfeature.png",
                "workflow": "wf1"
            },
            {
                "key": "issueType2",
                "name": "Bug",
                "description": "A problem which impairs or prevents the functions of the product.",
                "icon": "/images/icons/bug.png"
            },
            {
                "key": "issueType3",
                "name": "Sub-Task",
                "description": "The sub-task of the issue",
                "icon": "/images/icons/subtask_alternate.png",
                "sub-task": true,
                "workflow": "wf2"
            }
        ]
    },
    "workflow-scheme":
    {
        "name": "project.workflow.scheme.name",
        "description": "project.workflow.scheme.description",
        "default-workflow": "wf1",
        "workflows": [
            {
                "key": "wf1",
                "name": "project.workflow.wf1.name",
                "workflow-bundle": "/wfb/Issue-Tracking-Workflow.jwb"
            },
            {
                "key": "wf2",
                "name": "project.workflow.wf2.name",
                "workflow-bundle": "/wfb/Software-Development-Workflow.jwb"
            }
        ]
    }
}